{
"type": "FeatureCollection",
"name": "WREXH_14_toilets",
"crs": { "type": "name", "properties": { "name": "urn:ogc:def:crs:OGC:1.3:CRS84" } },
"features": [
{ "type": "Feature", "properties": { "name": "Tesco", "payment_info": "Free", "accessible": "Unknown", "radar": "Unknown", "women": "Unknown", "men": "Unknown", "baby_change": "Unknown", "Mon": "Unknown", "Tue": "Unknown", "Wed": "Unknown", "Thu": "Unknown", "Fri": "Unknown", "Sat": "Unknown", "Sun": "Unknown", "index_right": 10, "park_offical_id": "WREXH_14" }, "geometry": { "type": "Point", "coordinates": [ -2.987396717, 53.046173096 ] } }
]
}
