{
"type": "FeatureCollection",
"name": "WREXH_47_toilets",
"crs": { "type": "name", "properties": { "name": "urn:ogc:def:crs:OGC:1.3:CRS84" } },
"features": [
{ "type": "Feature", "properties": { "name": "Minera Lead Mines Car Park", "payment_info": "Free", "accessible": "True", "radar": "True", "women": "True", "men": "True", "baby_change": "Unknown", "Mon": "Unknown", "Tue": "Unknown", "Wed": "Unknown", "Thu": "Unknown", "Fri": "Unknown", "Sat": "Unknown", "Sun": "Unknown", "index_right": 46, "park_offical_id": "WREXH_47" }, "geometry": { "type": "Point", "coordinates": [ -3.081474602, 53.050720191 ] } }
]
}
