{
"type": "FeatureCollection",
"name": "DENBI_7",
"crs": { "type": "name", "properties": { "name": "urn:ogc:def:crs:OGC:1.3:CRS84" } },
"features": [
{ "type": "Feature", "properties": { "osm_id": 12894273484, "name": null, "amenity": null, "man_made": null, "leisure": "picnic_table", "playground": null, "memorial": null }, "geometry": { "type": "Point", "coordinates": [ -3.411414, 53.0568631 ] } },
{ "type": "Feature", "properties": { "osm_id": 12894316219, "name": null, "amenity": null, "man_made": null, "leisure": "picnic_table", "playground": null, "memorial": null }, "geometry": { "type": "Point", "coordinates": [ -3.4115647, 53.0568897 ] } },
{ "type": "Feature", "properties": { "osm_id": 12894260379, "name": null, "amenity": null, "man_made": null, "leisure": "picnic_table", "playground": null, "memorial": null }, "geometry": { "type": "Point", "coordinates": [ -3.4119693, 53.0569673 ] } },
{ "type": "Feature", "properties": { "osm_id": 12894303666, "name": null, "amenity": null, "man_made": null, "leisure": "picnic_table", "playground": null, "memorial": null }, "geometry": { "type": "Point", "coordinates": [ -3.4118282, 53.0569868 ] } }
]
}
