{
"type": "FeatureCollection",
"name": "CONWY_15",
"crs": { "type": "name", "properties": { "name": "urn:ogc:def:crs:OGC:1.3:CRS84" } },
"features": [
{ "type": "Feature", "properties": { "osm_id": 3308064886, "name": null, "amenity": null, "man_made": null, "leisure": "picnic_table", "playground": null, "memorial": null }, "geometry": { "type": "Point", "coordinates": [ -3.5236255, 53.3022983 ] } },
{ "type": "Feature", "properties": { "osm_id": 3308064885, "name": null, "amenity": null, "man_made": null, "leisure": "picnic_table", "playground": null, "memorial": null }, "geometry": { "type": "Point", "coordinates": [ -3.5237145, 53.3023183 ] } },
{ "type": "Feature", "properties": { "osm_id": 3308064915, "name": null, "amenity": null, "man_made": null, "leisure": "picnic_table", "playground": null, "memorial": null }, "geometry": { "type": "Point", "coordinates": [ -3.5235625, 53.3023227 ] } },
{ "type": "Feature", "properties": { "osm_id": 3308064884, "name": null, "amenity": null, "man_made": null, "leisure": "picnic_table", "playground": null, "memorial": null }, "geometry": { "type": "Point", "coordinates": [ -3.5236533, 53.3023437 ] } },
{ "type": "Feature", "properties": { "osm_id": 3308064883, "name": null, "amenity": null, "man_made": null, "leisure": "picnic_table", "playground": null, "memorial": null }, "geometry": { "type": "Point", "coordinates": [ -3.5237182, 53.3023847 ] } },
{ "type": "Feature", "properties": { "osm_id": 3308064914, "name": null, "amenity": null, "man_made": null, "leisure": "picnic_table", "playground": null, "memorial": null }, "geometry": { "type": "Point", "coordinates": [ -3.5231603, 53.3026549 ] } }
]
}
