{
"type": "FeatureCollection",
"name": "WREXH_47",
"crs": { "type": "name", "properties": { "name": "urn:ogc:def:crs:OGC:1.3:CRS84" } },
"features": [
{ "type": "Feature", "properties": { "osm_id": 5509424367, "name": null, "amenity": null, "man_made": null, "leisure": "picnic_table", "playground": null, "memorial": null }, "geometry": { "type": "Point", "coordinates": [ -3.0809057, 53.0501852 ] } },
{ "type": "Feature", "properties": { "osm_id": 5509424365, "name": null, "amenity": null, "man_made": null, "leisure": "picnic_table", "playground": null, "memorial": null }, "geometry": { "type": "Point", "coordinates": [ -3.0809045, 53.050246 ] } },
{ "type": "Feature", "properties": { "osm_id": 5509424366, "name": null, "amenity": null, "man_made": null, "leisure": "picnic_table", "playground": null, "memorial": null }, "geometry": { "type": "Point", "coordinates": [ -3.0810118, 53.0502644 ] } },
{ "type": "Feature", "properties": { "osm_id": 5509424364, "name": null, "amenity": null, "man_made": null, "leisure": "picnic_table", "playground": null, "memorial": null }, "geometry": { "type": "Point", "coordinates": [ -3.0810362, 53.050334 ] } },
{ "type": "Feature", "properties": { "osm_id": 12864186647, "name": null, "amenity": "bench", "man_made": null, "leisure": null, "playground": null, "memorial": null }, "geometry": { "type": "Point", "coordinates": [ -3.0839719, 53.0504409 ] } },
{ "type": "Feature", "properties": { "osm_id": 12864183993, "name": null, "amenity": "bench", "man_made": null, "leisure": null, "playground": null, "memorial": null }, "geometry": { "type": "Point", "coordinates": [ -3.0847253, 53.0510677 ] } },
{ "type": "Feature", "properties": { "osm_id": 12864221739, "name": null, "amenity": "bench", "man_made": null, "leisure": null, "playground": null, "memorial": null }, "geometry": { "type": "Point", "coordinates": [ -3.0942741, 53.0549061 ] } }
]
}
