{
"type": "FeatureCollection",
"name": "CONWY_75_toilets",
"crs": { "type": "name", "properties": { "name": "urn:ogc:def:crs:OGC:1.3:CRS84" } },
"features": [
{ "type": "Feature", "properties": { "name": "Llandudno George Street", "payment_info": "050", "accessible": "False", "radar": "False", "women": "True", "men": "True", "baby_change": "Unknown", "Mon": "09:00-17:00", "Tue": "09:00-17:00", "Wed": "09:00-17:00", "Thu": "09:00-17:00", "Fri": "09:00-17:00", "Sat": "09:00-17:00", "Sun": "09:00-17:00", "index_right": 77, "park_offical_id": "CONWY_75" }, "geometry": { "type": "Point", "coordinates": [ -3.8313669, 53.324594 ] } }
]
}
