{
"type": "FeatureCollection",
"name": "01e518404778_visibility",
"crs": { "type": "name", "properties": { "name": "urn:ogc:def:crs:OGC:1.3:CRS84" } },
"features": [
{ "type": "Feature", "properties": { "visible_points": 8, "total_points": 58, "visibility_pct": 13.793103448275861 }, "geometry": { "type": "Point", "coordinates": [ -3.777926256605082, 53.31661766947451 ] } },
{ "type": "Feature", "properties": { "visible_points": 7, "total_points": 58, "visibility_pct": 12.068965517241379 }, "geometry": { "type": "Point", "coordinates": [ -3.777718365443948, 53.316620769668262 ] } },
{ "type": "Feature", "properties": { "visible_points": 7, "total_points": 56, "visibility_pct": 12.5 }, "geometry": { "type": "Point", "coordinates": [ -3.77751047424445, 53.316623869500091 ] } },
{ "type": "Feature", "properties": { "visible_points": 0, "total_points": 51, "visibility_pct": 0.0 }, "geometry": { "type": "Point", "coordinates": [ -3.777302583006593, 53.316626968969949 ] } },
{ "type": "Feature", "properties": { "visible_points": 10, "total_points": 58, "visibility_pct": 17.241379310344829 }, "geometry": { "type": "Point", "coordinates": [ -3.778034681481039, 53.316723933484006 ] } },
{ "type": "Feature", "properties": { "visible_points": 11, "total_points": 58, "visibility_pct": 18.96551724137931 }, "geometry": { "type": "Point", "coordinates": [ -3.777826789817457, 53.316727033874614 ] } },
{ "type": "Feature", "properties": { "visible_points": 10, "total_points": 58, "visibility_pct": 17.241379310344829 }, "geometry": { "type": "Point", "coordinates": [ -3.777618898115506, 53.31673013390327 ] } },
{ "type": "Feature", "properties": { "visible_points": 5, "total_points": 56, "visibility_pct": 8.9285714285714288 }, "geometry": { "type": "Point", "coordinates": [ -3.777411006375198, 53.316733233569984 ] } },
{ "type": "Feature", "properties": { "visible_points": 0, "total_points": 51, "visibility_pct": 0.0 }, "geometry": { "type": "Point", "coordinates": [ -3.777203114596527, 53.316736332874733 ] } },
{ "type": "Feature", "properties": { "visible_points": 8, "total_points": 56, "visibility_pct": 14.285714285714285 }, "geometry": { "type": "Point", "coordinates": [ -3.778143106897813, 53.316830197384782 ] } },
{ "type": "Feature", "properties": { "visible_points": 6, "total_points": 58, "visibility_pct": 10.344827586206897 }, "geometry": { "type": "Point", "coordinates": [ -3.777935214731781, 53.316833297972217 ] } },
{ "type": "Feature", "properties": { "visible_points": 7, "total_points": 58, "visibility_pct": 12.068965517241379 }, "geometry": { "type": "Point", "coordinates": [ -3.777727322527374, 53.316836398197729 ] } },
{ "type": "Feature", "properties": { "visible_points": 3, "total_points": 58, "visibility_pct": 5.1724137931034484 }, "geometry": { "type": "Point", "coordinates": [ -3.777519430284615, 53.31683949806127 ] } },
{ "type": "Feature", "properties": { "visible_points": 0, "total_points": 55, "visibility_pct": 0.0 }, "geometry": { "type": "Point", "coordinates": [ -3.777311538003485, 53.316842597562861 ] } },
{ "type": "Feature", "properties": { "visible_points": 0, "total_points": 52, "visibility_pct": 0.0 }, "geometry": { "type": "Point", "coordinates": [ -3.778251532918862, 53.316936461138695 ] } },
{ "type": "Feature", "properties": { "visible_points": 1, "total_points": 56, "visibility_pct": 1.7857142857142856 }, "geometry": { "type": "Point", "coordinates": [ -3.778043640254546, 53.316939561918907 ] } },
{ "type": "Feature", "properties": { "visible_points": 0, "total_points": 58, "visibility_pct": 0.0 }, "geometry": { "type": "Point", "coordinates": [ -3.777835747551853, 53.316942662336956 ] } },
{ "type": "Feature", "properties": { "visible_points": 0, "total_points": 58, "visibility_pct": 0.0 }, "geometry": { "type": "Point", "coordinates": [ -3.777627854810775, 53.316945762392827 ] } },
{ "type": "Feature", "properties": { "visible_points": 1, "total_points": 51, "visibility_pct": 1.9607843137254901 }, "geometry": { "type": "Point", "coordinates": [ -3.778152066497404, 53.317045825696546 ] } },
{ "type": "Feature", "properties": { "visible_points": 0, "total_points": 55, "visibility_pct": 0.0 }, "geometry": { "type": "Point", "coordinates": [ -3.777944173296129, 53.317048926303855 ] } },
{ "type": "Feature", "properties": { "visible_points": 0, "total_points": 57, "visibility_pct": 0.0 }, "geometry": { "type": "Point", "coordinates": [ -3.77773628005647, 53.317052026548772 ] } }
]
}
