{
"type": "FeatureCollection",
"name": "13647f226c11_visibility",
"crs": { "type": "name", "properties": { "name": "urn:ogc:def:crs:OGC:1.3:CRS84" } },
"features": [
{ "type": "Feature", "properties": { "visible_points": 4, "total_points": 57, "visibility_pct": 7.0175438596491224 }, "geometry": { "type": "Point", "coordinates": [ -3.52115552807618, 53.302191279017393 ] } },
{ "type": "Feature", "properties": { "visible_points": 7, "total_points": 57, "visibility_pct": 12.280701754385964 }, "geometry": { "type": "Point", "coordinates": [ -3.520947678053168, 53.302193929606375 ] } },
{ "type": "Feature", "properties": { "visible_points": 1, "total_points": 54, "visibility_pct": 1.8518518518518516 }, "geometry": { "type": "Point", "coordinates": [ -3.52073982799784, 53.302196579833875 ] } },
{ "type": "Feature", "properties": { "visible_points": 1, "total_points": 49, "visibility_pct": 2.0408163265306123 }, "geometry": { "type": "Point", "coordinates": [ -3.520531977910201, 53.30219922969988 ] } },
{ "type": "Feature", "properties": { "visible_points": 6, "total_points": 58, "visibility_pct": 10.344827586206897 }, "geometry": { "type": "Point", "coordinates": [ -3.52126328749709, 53.302297783032181 ] } },
{ "type": "Feature", "properties": { "visible_points": 11, "total_points": 58, "visibility_pct": 18.96551724137931 }, "geometry": { "type": "Point", "coordinates": [ -3.521055436978922, 53.302300433825117 ] } },
{ "type": "Feature", "properties": { "visible_points": 2, "total_points": 58, "visibility_pct": 3.4482758620689653 }, "geometry": { "type": "Point", "coordinates": [ -3.520847586428433, 53.302303084256543 ] } },
{ "type": "Feature", "properties": { "visible_points": 5, "total_points": 57, "visibility_pct": 8.7719298245614024 }, "geometry": { "type": "Point", "coordinates": [ -3.521371047445473, 53.302404286930781 ] } },
{ "type": "Feature", "properties": { "visible_points": 9, "total_points": 58, "visibility_pct": 15.517241379310345 }, "geometry": { "type": "Point", "coordinates": [ -3.521163196432138, 53.302406937927657 ] } },
{ "type": "Feature", "properties": { "visible_points": 5, "total_points": 58, "visibility_pct": 8.6206896551724146 }, "geometry": { "type": "Point", "coordinates": [ -3.520955345386484, 53.302409588563044 ] } },
{ "type": "Feature", "properties": { "visible_points": 7, "total_points": 53, "visibility_pct": 13.20754716981132 }, "geometry": { "type": "Point", "coordinates": [ -3.521478807921326, 53.302510790713178 ] } },
{ "type": "Feature", "properties": { "visible_points": 12, "total_points": 57, "visibility_pct": 21.052631578947366 }, "geometry": { "type": "Point", "coordinates": [ -3.521270956412823, 53.302513441914009 ] } },
{ "type": "Feature", "properties": { "visible_points": 6, "total_points": 58, "visibility_pct": 10.344827586206897 }, "geometry": { "type": "Point", "coordinates": [ -3.521063104872005, 53.302516092753329 ] } },
{ "type": "Feature", "properties": { "visible_points": 5, "total_points": 47, "visibility_pct": 10.638297872340425 }, "geometry": { "type": "Point", "coordinates": [ -3.521586568924651, 53.302617294379381 ] } },
{ "type": "Feature", "properties": { "visible_points": 3, "total_points": 52, "visibility_pct": 5.7692307692307692 }, "geometry": { "type": "Point", "coordinates": [ -3.521378716920982, 53.30261994578413 ] } },
{ "type": "Feature", "properties": { "visible_points": 4, "total_points": 56, "visibility_pct": 7.1428571428571423 }, "geometry": { "type": "Point", "coordinates": [ -3.521170864884998, 53.302622596827433 ] } },
{ "type": "Feature", "properties": { "visible_points": 0, "total_points": 58, "visibility_pct": 0.0 }, "geometry": { "type": "Point", "coordinates": [ -3.520963012816689, 53.302625247509233 ] } },
{ "type": "Feature", "properties": { "visible_points": 9, "total_points": 49, "visibility_pct": 18.367346938775512 }, "geometry": { "type": "Point", "coordinates": [ -3.52127862542547, 53.302729100785328 ] } },
{ "type": "Feature", "properties": { "visible_points": 7, "total_points": 52, "visibility_pct": 13.461538461538462 }, "geometry": { "type": "Point", "coordinates": [ -3.521070772861987, 53.302731751671075 ] } },
{ "type": "Feature", "properties": { "visible_points": 5, "total_points": 52, "visibility_pct": 9.6153846153846168 }, "geometry": { "type": "Point", "coordinates": [ -3.520862920266194, 53.302734402195355 ] } }
]
}
