{
"type": "FeatureCollection",
"name": "6bb7085f89ea_visibility",
"crs": { "type": "name", "properties": { "name": "urn:ogc:def:crs:OGC:1.3:CRS84" } },
"features": [
{ "type": "Feature", "properties": { "visible_points": 0, "total_points": 48, "visibility_pct": 0.0 }, "geometry": { "type": "Point", "coordinates": [ -3.764189920185157, 53.30342031816491 ] } },
{ "type": "Feature", "properties": { "visible_points": 9, "total_points": 50, "visibility_pct": 18.0 }, "geometry": { "type": "Point", "coordinates": [ -3.763982091654713, 53.303423393682131 ] } },
{ "type": "Feature", "properties": { "visible_points": 13, "total_points": 50, "visibility_pct": 26.0 }, "geometry": { "type": "Point", "coordinates": [ -3.763774263086098, 53.303426468837614 ] } },
{ "type": "Feature", "properties": { "visible_points": 0, "total_points": 50, "visibility_pct": 0.0 }, "geometry": { "type": "Point", "coordinates": [ -3.763566434479315, 53.303429543631417 ] } },
{ "type": "Feature", "properties": { "visible_points": 5, "total_points": 46, "visibility_pct": 10.869565217391305 }, "geometry": { "type": "Point", "coordinates": [ -3.763358605834376, 53.303432618063546 ] } },
{ "type": "Feature", "properties": { "visible_points": 4, "total_points": 46, "visibility_pct": 8.695652173913043 }, "geometry": { "type": "Point", "coordinates": [ -3.764298276958069, 53.303526595504977 ] } },
{ "type": "Feature", "properties": { "visible_points": 6, "total_points": 50, "visibility_pct": 12.0 }, "geometry": { "type": "Point", "coordinates": [ -3.764090447923173, 53.303529671220311 ] } },
{ "type": "Feature", "properties": { "visible_points": 14, "total_points": 50, "visibility_pct": 28.000000000000004 }, "geometry": { "type": "Point", "coordinates": [ -3.763882618850102, 53.303532746573957 ] } },
{ "type": "Feature", "properties": { "visible_points": 8, "total_points": 50, "visibility_pct": 16.0 }, "geometry": { "type": "Point", "coordinates": [ -3.763674789738863, 53.303535821565895 ] } },
{ "type": "Feature", "properties": { "visible_points": 4, "total_points": 50, "visibility_pct": 8.0 }, "geometry": { "type": "Point", "coordinates": [ -3.763466960589467, 53.303538896196144 ] } },
{ "type": "Feature", "properties": { "visible_points": 0, "total_points": 43, "visibility_pct": 0.0 }, "geometry": { "type": "Point", "coordinates": [ -3.763259131401905, 53.303541970464671 ] } },
{ "type": "Feature", "properties": { "visible_points": 1, "total_points": 43, "visibility_pct": 2.3255813953488373 }, "geometry": { "type": "Point", "coordinates": [ -3.764406634273607, 53.303632872734887 ] } },
{ "type": "Feature", "properties": { "visible_points": 7, "total_points": 49, "visibility_pct": 14.285714285714285 }, "geometry": { "type": "Point", "coordinates": [ -3.764198804734255, 53.30363594864837 ] } },
{ "type": "Feature", "properties": { "visible_points": 14, "total_points": 50, "visibility_pct": 28.000000000000004 }, "geometry": { "type": "Point", "coordinates": [ -3.763990975156727, 53.303639024200137 ] } },
{ "type": "Feature", "properties": { "visible_points": 15, "total_points": 50, "visibility_pct": 30.0 }, "geometry": { "type": "Point", "coordinates": [ -3.763783145541033, 53.303642099390224 ] } },
{ "type": "Feature", "properties": { "visible_points": 10, "total_points": 50, "visibility_pct": 20.0 }, "geometry": { "type": "Point", "coordinates": [ -3.763575315887175, 53.303645174218595 ] } },
{ "type": "Feature", "properties": { "visible_points": 6, "total_points": 46, "visibility_pct": 13.043478260869565 }, "geometry": { "type": "Point", "coordinates": [ -3.763367486195149, 53.303648248685263 ] } },
{ "type": "Feature", "properties": { "visible_points": 12, "total_points": 49, "visibility_pct": 24.489795918367346 }, "geometry": { "type": "Point", "coordinates": [ -3.764099332005987, 53.303745301716177 ] } },
{ "type": "Feature", "properties": { "visible_points": 12, "total_points": 50, "visibility_pct": 24.0 }, "geometry": { "type": "Point", "coordinates": [ -3.763891501885829, 53.303748377104398 ] } },
{ "type": "Feature", "properties": { "visible_points": 16, "total_points": 50, "visibility_pct": 32.0 }, "geometry": { "type": "Point", "coordinates": [ -3.763683671727506, 53.303751452130903 ] } },
{ "type": "Feature", "properties": { "visible_points": 13, "total_points": 47, "visibility_pct": 27.659574468085108 }, "geometry": { "type": "Point", "coordinates": [ -3.76347584153102, 53.303754526795714 ] } },
{ "type": "Feature", "properties": { "visible_points": 0, "total_points": 41, "visibility_pct": 0.0 }, "geometry": { "type": "Point", "coordinates": [ -3.763268011296366, 53.303757601098809 ] } }
]
}
