{
"type": "FeatureCollection",
"name": "ed64d977ad04_visibility",
"crs": { "type": "name", "properties": { "name": "urn:ogc:def:crs:OGC:1.3:CRS84" } },
"features": [
{ "type": "Feature", "properties": { "visible_points": 0, "total_points": 57, "visibility_pct": 0.0 }, "geometry": { "type": "Point", "coordinates": [ -4.525905424273868, 53.376120260910959 ] } },
{ "type": "Feature", "properties": { "visible_points": 3, "total_points": 54, "visibility_pct": 5.5555555555555554 }, "geometry": { "type": "Point", "coordinates": [ -4.525697349343134, 53.376124667325968 ] } },
{ "type": "Feature", "properties": { "visible_points": 0, "total_points": 59, "visibility_pct": 0.0 }, "geometry": { "type": "Point", "coordinates": [ -4.526015841383376, 53.37622581574719 ] } },
{ "type": "Feature", "properties": { "visible_points": 0, "total_points": 58, "visibility_pct": 0.0 }, "geometry": { "type": "Point", "coordinates": [ -4.525807765961361, 53.376230222361308 ] } },
{ "type": "Feature", "properties": { "visible_points": 1, "total_points": 55, "visibility_pct": 1.8181818181818181 }, "geometry": { "type": "Point", "coordinates": [ -4.525599690484991, 53.376234628613027 ] } },
{ "type": "Feature", "properties": { "visible_points": 0, "total_points": 59, "visibility_pct": 0.0 }, "geometry": { "type": "Point", "coordinates": [ -4.526126259038509, 53.376331370472386 ] } },
{ "type": "Feature", "properties": { "visible_points": 0, "total_points": 59, "visibility_pct": 0.0 }, "geometry": { "type": "Point", "coordinates": [ -4.52591818312521, 53.376335777285618 ] } },
{ "type": "Feature", "properties": { "visible_points": 0, "total_points": 58, "visibility_pct": 0.0 }, "geometry": { "type": "Point", "coordinates": [ -4.525710107157556, 53.376340183736446 ] } },
{ "type": "Feature", "properties": { "visible_points": 0, "total_points": 55, "visibility_pct": 0.0 }, "geometry": { "type": "Point", "coordinates": [ -4.525502031135563, 53.376344589824889 ] } },
{ "type": "Feature", "properties": { "visible_points": 2, "total_points": 59, "visibility_pct": 3.3898305084745761 }, "geometry": { "type": "Point", "coordinates": [ -4.526236677239277, 53.376436925086523 ] } },
{ "type": "Feature", "properties": { "visible_points": 0, "total_points": 59, "visibility_pct": 0.0 }, "geometry": { "type": "Point", "coordinates": [ -4.526028600834688, 53.376441332098899 ] } },
{ "type": "Feature", "properties": { "visible_points": 0, "total_points": 59, "visibility_pct": 0.0 }, "geometry": { "type": "Point", "coordinates": [ -4.525820524375748, 53.376445738748842 ] } },
{ "type": "Feature", "properties": { "visible_points": 0, "total_points": 58, "visibility_pct": 0.0 }, "geometry": { "type": "Point", "coordinates": [ -4.525612447862459, 53.376450145036387 ] } },
{ "type": "Feature", "properties": { "visible_points": 0, "total_points": 54, "visibility_pct": 0.0 }, "geometry": { "type": "Point", "coordinates": [ -4.525404371294825, 53.376454550961533 ] } },
{ "type": "Feature", "properties": { "visible_points": 0, "total_points": 54, "visibility_pct": 0.0 }, "geometry": { "type": "Point", "coordinates": [ -4.526347095985684, 53.376542479589638 ] } },
{ "type": "Feature", "properties": { "visible_points": 0, "total_points": 59, "visibility_pct": 0.0 }, "geometry": { "type": "Point", "coordinates": [ -4.526139019089809, 53.376546886801123 ] } },
{ "type": "Feature", "properties": { "visible_points": 0, "total_points": 59, "visibility_pct": 0.0 }, "geometry": { "type": "Point", "coordinates": [ -4.525930942139574, 53.376551293650188 ] } },
{ "type": "Feature", "properties": { "visible_points": 0, "total_points": 59, "visibility_pct": 0.0 }, "geometry": { "type": "Point", "coordinates": [ -4.525722865134993, 53.376555700136848 ] } },
{ "type": "Feature", "properties": { "visible_points": 0, "total_points": 56, "visibility_pct": 0.0 }, "geometry": { "type": "Point", "coordinates": [ -4.52551478807606, 53.37656010626111 ] } },
{ "type": "Feature", "properties": { "visible_points": 0, "total_points": 47, "visibility_pct": 0.0 }, "geometry": { "type": "Point", "coordinates": [ -4.525306710962785, 53.376564512022952 ] } },
{ "type": "Feature", "properties": { "visible_points": 1, "total_points": 45, "visibility_pct": 2.2222222222222223 }, "geometry": { "type": "Point", "coordinates": [ -4.526457515277732, 53.376648033981716 ] } },
{ "type": "Feature", "properties": { "visible_points": 0, "total_points": 52, "visibility_pct": 0.0 }, "geometry": { "type": "Point", "coordinates": [ -4.526249437890564, 53.376652441392302 ] } },
{ "type": "Feature", "properties": { "visible_points": 3, "total_points": 56, "visibility_pct": 5.3571428571428568 }, "geometry": { "type": "Point", "coordinates": [ -4.526041360449041, 53.376656848440497 ] } },
{ "type": "Feature", "properties": { "visible_points": 1, "total_points": 56, "visibility_pct": 1.7857142857142856 }, "geometry": { "type": "Point", "coordinates": [ -4.525833282953162, 53.376661255126294 ] } }
]
}
