{
"type": "FeatureCollection",
"name": "FLINT_168_toilets",
"crs": { "type": "name", "properties": { "name": "urn:ogc:def:crs:OGC:1.3:CRS84" } },
"features": [
{ "type": "Feature", "properties": { "name": "Unknown", "payment_info": "Free", "accessible": "False", "radar": "Unknown", "women": "Unknown", "men": "Unknown", "baby_change": "Unknown", "Mon": "Unknown", "Tue": "Unknown", "Wed": "Unknown", "Thu": "Unknown", "Fri": "Unknown", "Sat": "Unknown", "Sun": "Unknown", "index_right": 40, "park_offical_id": "FLINT_168" }, "geometry": { "type": "Point", "coordinates": [ -3.222588301, 53.273464453 ] } }
]
}
