{
"type": "FeatureCollection",
"name": "FLINT_85_toilets",
"crs": { "type": "name", "properties": { "name": "urn:ogc:def:crs:OGC:1.3:CRS84" } },
"features": [
{ "type": "Feature", "properties": { "name": "Flint Railway Station", "payment_info": "Free", "accessible": "False", "radar": "False", "women": "Unknown", "men": "Unknown", "baby_change": "False", "Mon": "Unknown", "Tue": "Unknown", "Wed": "Unknown", "Thu": "Unknown", "Fri": "Unknown", "Sat": "Unknown", "Sun": "Unknown", "index_right": 159, "park_offical_id": "FLINT_85" }, "geometry": { "type": "Point", "coordinates": [ -3.132530451, 53.249703333 ] } }
]
}
